cx_tools/__init__.py
cx_tools/filesize_counter.py
cx_tools/app/__init__.py
cx_tools/app/config_manager.py
cx_tools/app/iappenv.py
cx_tools/app/iapplication.py
cx_tools/app/progress_task_agent.py
cx_tools/app/safe_error.py
ffpretty/__init__.py
ffpretty/appenv.py
ffpretty/application.py
jpegger/__init__.py
jpegger/appenv.py
jpegger/simple_appcontext.py
jpegger/simple_application.py
jpegger/simple_filter_chain_builder.py
jpegger/simple_mission_builder.py
jpegger/components/__init__.py
jpegger/components/errors.py
jpegger/components/format_database.py
jpegger/components/formats.csv
jpegger/components/mission.py
jpegger/components/mission_runner.py
jpegger/filters/__init__.py
jpegger/filters/auto_resize.py
jpegger/filters/colorspace.py
jpegger/filters/image_filter.py
jpegger/filters/image_filter_chain.py
jpegger/filters/resize.py
media_killer/__init__.py
media_killer/appcontext.py
media_killer/appenv.py
media_killer/application.py
media_killer/banner.txt
media_killer/example_preset.toml
media_killer/help.md
media_killer/mk_help_info.py
media_killer/components/__init__.py
media_killer/components/argument_group.py
media_killer/components/exception.py
media_killer/components/input_scanner.py
media_killer/components/mission.py
media_killer/components/mission_arranger.py
media_killer/components/mission_maker.py
media_killer/components/mission_master.py
media_killer/components/mission_runner.py
media_killer/components/mission_xml.py
media_killer/components/preset.py
media_killer/components/preset_tag_replacer.py
media_killer/components/script_maker.py
media_killer/components/source_expander.py
media_scout/__init__.py
media_scout/appenv.py
media_scout/application.py
media_scout/arg_parser.py
media_scout/help.md
media_scout/inspectors/__init__.py
media_scout/inspectors/edl_inspector.py
media_scout/inspectors/fcpxml_inspector.py
media_scout/inspectors/filelist_inspector.py
media_scout/inspectors/inspector_chain.py
media_scout/inspectors/inspector_info.py
cxalio_studio_tools-0.5.1.2.dist-info/METADATA
cxalio_studio_tools-0.5.1.2.dist-info/WHEEL
cxalio_studio_tools-0.5.1.2.dist-info/entry_points.txt
cxalio_studio_tools-0.5.1.2.dist-info/RECORD
