Metadata-Version: 2.4
Name: cxalio-studio-tools
Version: 0.5.1.2
Summary: Add your description here
Requires-Python: >=3.12
Requires-Dist: cachetools>=5.5.2
Requires-Dist: cx-studio
Requires-Dist: cx-wealth
Requires-Dist: pillow>=11.2.1
Requires-Dist: pydantic>=2.11.4
Requires-Dist: python-box[all]~=7.0
Requires-Dist: rich-argparse>=1.7.0
Requires-Dist: rich>=14.0.0
Requires-Dist: ulid-py>=1.1.0
